blend2d/blend2d.lib
blend2d/nanobind-static.lib
blend2d/_capi.exp
blend2d/_capi.lib
blend2d/_capi.pyd
blend2d/__init__.py
blend2d/tests/test_basic.py
blend2d/tests/test_comprehensive.py
blend2d/tests/__init__.py
blend2d_python-1.0.0.dist-info/DELVEWHEEL
blend2d_python-1.0.0.dist-info/METADATA
blend2d_python-1.0.0.dist-info/RECORD
blend2d_python-1.0.0.dist-info/top_level.txt
blend2d_python-1.0.0.dist-info/WHEEL
blend2d_python-1.0.0.dist-info/licenses/LICENSE
blend2d_python.libs/.load-order-blend2d_python-1.0.0
blend2d_python.libs/msvcp140-a4c2229bdc2a2a630acdc095b4d86008.dll
